{
    "mount_base_dir": false,
    "actions": [
        {
            "call": {
                "func": "args_sizes_get",
                "results": [
                    { "resource": 0 },
                    { "resource": 1 }
                ]
            }
        },
        {
            "call": {
                "func": "args_get",
                "params": [
                    {
                        "value": {
                            "pointer": {
                                "alloc_from_resource": 0
                            }
                        }
                    },
                    { "value": { "pointer": { "alloc_from_resource": 1 } } }
                ]
            }
        }
    ]
}
